AUTHORS
ChangeLog
README.rst
requirements.txt
setup.cfg
setup.py
tox.ini
tests/test_cycle.py
tests/test_sort.py
tests/samples/sam2.rds
tests/samples/sample.rds
tests/samples/ttt/list.txt
ttr/__init__.py
ttr.rdsutils.egg-info/PKG-INFO
ttr.rdsutils.egg-info/SOURCES.txt
ttr.rdsutils.egg-info/dependency_links.txt
ttr.rdsutils.egg-info/entry_points.txt
ttr.rdsutils.egg-info/namespace_packages.txt
ttr.rdsutils.egg-info/not-zip-safe
ttr.rdsutils.egg-info/pbr.json
ttr.rdsutils.egg-info/requires.txt
ttr.rdsutils.egg-info/top_level.txt
ttr/rdsutils/__init__.py
ttr/rdsutils/rds_concat.py
ttr/rdsutils/rds_cycle.py
ttr/rdsutils/rds_sort.py