Metadata-Version: 1.1
Name: ttr.rdsutils
Version: 0.1.0
Summary: Command line utilities for working with raw RDS data files
Home-page: https://turbotmc.com
Author: TamTam Research
Author-email: jan.vlcinsky@tamtamresearch.com
License: BSD
Keywords: RDS
Platform: UNKNOWN
Classifier: Development Status :: 4 - Beta
Classifier: Environment :: Console
Classifier: Intended Audience :: Developers
Classifier: Intended Audience :: Information Technology
Classifier: Operating System :: OS Independent
Classifier: Programming Language :: Python
